{
  "notes": [
    {
      "id": "q_001",
      "question": "What is the difference between '==' and '==='?",
      "answer": "== checks value with type coercion. === checks value and type (strict).",
      "example": "5 == '5' // true | 5 === '5' // false"
    },
    {
      "id": "q_002",
      "question": "What is 'this' keyword in JavaScript?",
      "answer": "'this' refers to the object executing the function.",
      "example": "const obj = { name: 'JS', show() { console.log(this.name); } };"
    },
    {
      "id": "q_003",
      "question": "What is NaN?",
      "answer": "NaN means Not-a-Number. It represents invalid number results.",
      "example": "parseInt('Hello'); // NaN"
    },
    {
      "id": "q_004",
      "question": "Difference between null and undefined?",
      "answer": "undefined = declared but not assigned. null = empty value assigned.",
      "example": "let a; // undefined | let b = null;"
    },
    {
      "id": "q_005",
      "question": "What is Closure?",
      "answer": "A function that remembers its lexical scope even when executed outside.",
      "example": "function outer(){ let x=1; return ()=>x++; }"
    }
  ]
}
